<?xml version="1.0"?>
<method xmlns:xsi="http://www.w3.org/2001/XMLSchema-instance" xmlns:xsd="http://www.w3.org/2001/XMLSchema" xsi:type="OrmOtherMethod" id="16c1b09a-99a5-4a71-9abc-feacb05a85a2" lastModifiedUtc="2017-08-31T12:22:11.0476Z" name="btnSave0_OnClick" methodType="Other" actionType="None" returnMode="None" isInstance="false" containerName="InsertExchangeRate">
  <extendedMetaData />
  <ExtendedPropertiesCollection>
    <extendee type="Sage.Platform.Orm.Entities.OrmOtherMethod" />
  </ExtendedPropertiesCollection>
  <parameter>
    <OrmEntityMethodParam id="0aae9ac0-e8ac-43e5-b124-cea8964420bf" paramName="form" sequence="0" paramType="IInsertExchangeRate" />
    <OrmEntityMethodParam id="67935a36-7c47-4690-948e-47a7706bf937" paramName="args" sequence="0" paramType="EventArgs" />
  </parameter>
  <preExecuteTargets />
  <methodTargets />
  <postExecuteTargets />
</method>