<?xml version="1.0"?>
<DeletedItem>
  <id>52670235-2412-4057-a4cf-a17aa19531be</id>
  <url>\Portal\SlxClient\SupportFiles\jscript\Sage\MainView\EntityMgr\AddEditEntityFilter\templates\DistinctDetailsView.html</url>
  <caption>C:\Source Code\Gobi\Slx8.2HotFix-01\Model\Portal\SlxClient\SupportFiles\jscript\Sage\MainView\EntityMgr\AddEditEntityFilter\templates\DistinctDetailsView.html</caption>
  <extension>.html</extension>
  <modelId>73d4e7d0-a7fa-40ae-8b45-1ad7ed954154</modelId>
  <dateDeleted>2015-08-20T21:37:16.9251554Z</dateDeleted>
</DeletedItem>