<?xml version="1.0"?>
<method xmlns:xsi="http://www.w3.org/2001/XMLSchema-instance" xmlns:xsd="http://www.w3.org/2001/XMLSchema" id="7a861ee5-8477-4392-ab73-6632eb84649d" lastModifiedUtc="2015-08-24T15:23:51.0288905Z" name="OnBeforeUpdate" methodType="CrudEvent" actionType="None" returnMode="None">
  <extendedMetaData />
  <ExtendedPropertiesCollection>
    <extendee type="Sage.Platform.Orm.Entities.OrmEntityMethod" />
  </ExtendedPropertiesCollection>
  <parameter />
  <preExecuteTargets />
  <methodTargets>
    <methodTarget id="a0274554-967f-485a-bc7c-e09bd1cd9a66" lastModifiedUtc="2015-08-27T19:10:45.6702856Z" targetType="Sage.SalesLogix.ExchangeRate.Rules, Sage.SalesLogix.BusinessRules" targetMethod="OnBeforeUpdate" active="true">
      <ExtendedPropertiesCollection>
        <extendee type="Sage.Platform.Orm.Entities.OrmMethodTarget" />
      </ExtendedPropertiesCollection>
    </methodTarget>
  </methodTargets>
  <postExecuteTargets />
</method>