<?xml version="1.0"?>
<QuickForm xmlns:xsi="http://www.w3.org/2001/XMLSchema-instance" xmlns:xsd="http://www.w3.org/2001/XMLSchema" id="9b897b4d-078b-462a-9d5f-4d60cb47e763" DefinitionType="Sage.Platform.QuickForms.QuickFormMainDetailViewDefinition, Sage.Platform.QuickForms">
  <ActiveControl />
  <ImagePath />
  <LoadActions />
  <Name>ErpPayFromErpBillTos</Name>
  <ClientScriptIncludes />
  <ClientResourceKeys />
  <ExtendedProperties />
  <HelpFile />
  <ReadOnly>false</ReadOnly>
  <GeneratePrintView>false</GeneratePrintView>
  <Controls>
    <Control typeName="Sage.SalesLogix.QuickForms.QFControls.SDataGrid.QFSDataGrid, Sage.SalesLogix.QuickForms.QFControls">
      <QFSDataGrid>
        <Column>0</Column>
        <Row>0</Row>
        <HotKey>0</HotKey>
        <TabIndex>0</TabIndex>
        <ControlId>grdErpBillTo</ControlId>
        <DataBindings />
        <ControlLabelPlacement>left</ControlLabelPlacement>
        <ExtendedProperties />
        <CaptionAlignment>left</CaptionAlignment>
        <StyleScheme />
        <GenerateMember>false</GenerateMember>
        <ReadOnlyCondition>False</ReadOnlyCondition>
        <AppliedSecurity />
        <RelateToPropertyName>ErpPayFromBillTos</RelateToPropertyName>
        <PreviewField />
        <ResourceKind>
          <Name>erpPayFromBillTos</Name>
          <GetPredicate />
        </ResourceKind>
        <PathSegments />
        <Columns>
          <QFSDataLinkCol>
            <StyleScheme />
            <DataField>ERPBillTo.Name</DataField>
            <ColumnId>7001ebbf-1a58-411e-a6c0-2a97d44a97a1</ColumnId>
            <HorizontalAlignment>left</HorizontalAlignment>
            <HeaderAlignment>left</HeaderAlignment>
            <SortDirection>None</SortDirection>
            <IsSortable>true</IsSortable>
            <SortField>ErpBillTo.Name</SortField>
            <MultiCurrencyDependent>false</MultiCurrencyDependent>
            <Destination />
            <Image />
            <EntityIdField>ERPBillTo.Id</EntityIdField>
            <EntityTypeName>ERPBillTo</EntityTypeName>
            <Target />
            <AppliedSecurity />
            <HideCondition />
            <Width>-1</Width>
          </QFSDataLinkCol>
          <QFEditableCol>
            <StyleScheme />
            <DataField>ERPBillTo.Address.City</DataField>
            <ColumnId>32ebf6c2-c5e0-4e81-bf24-6678cbbd186d</ColumnId>
            <HorizontalAlignment>left</HorizontalAlignment>
            <HeaderAlignment>left</HeaderAlignment>
            <SortDirection>None</SortDirection>
            <IsSortable>true</IsSortable>
            <SortField>ERPBillTo.Address.City</SortField>
            <MultiCurrencyDependent>false</MultiCurrencyDependent>
            <IsEditable>false</IsEditable>
            <HideCondition />
            <Width>-1</Width>
            <CustomFormatter />
            <AbbreviationLength>0</AbbreviationLength>
          </QFEditableCol>
          <QFEditableCol>
            <StyleScheme />
            <DataField>ERPBillTo.Address.State</DataField>
            <ColumnId>1d11e0f9-fd1c-464c-97c0-a3807059e614</ColumnId>
            <HorizontalAlignment>left</HorizontalAlignment>
            <HeaderAlignment>left</HeaderAlignment>
            <SortDirection>None</SortDirection>
            <IsSortable>true</IsSortable>
            <SortField>ERPBillTo.Address.State</SortField>
            <MultiCurrencyDependent>false</MultiCurrencyDependent>
            <IsEditable>false</IsEditable>
            <HideCondition />
            <Width>-1</Width>
            <CustomFormatter />
            <AbbreviationLength>0</AbbreviationLength>
          </QFEditableCol>
          <QFEditableCol>
            <StyleScheme />
            <DataField>ERPBillTo.Address.Country</DataField>
            <ColumnId>1fab6e4f-9020-49a3-847a-ffc78ecadd4c</ColumnId>
            <HorizontalAlignment>left</HorizontalAlignment>
            <HeaderAlignment>left</HeaderAlignment>
            <SortDirection>None</SortDirection>
            <IsSortable>true</IsSortable>
            <SortField>ERPBillTo.Address.Country</SortField>
            <MultiCurrencyDependent>false</MultiCurrencyDependent>
            <IsEditable>false</IsEditable>
            <HideCondition />
            <Width>-1</Width>
            <CustomFormatter />
            <AbbreviationLength>0</AbbreviationLength>
          </QFEditableCol>
          <QFSDataPhoneCol>
            <StyleScheme />
            <DataField>ERPBillTo.MainPhone</DataField>
            <ColumnId>c6d0872a-6df2-4f12-bced-6101574b514c</ColumnId>
            <HorizontalAlignment>left</HorizontalAlignment>
            <HeaderAlignment>left</HeaderAlignment>
            <SortDirection>None</SortDirection>
            <IsSortable>true</IsSortable>
            <SortField>ERPBillTo.MainPhone</SortField>
            <MultiCurrencyDependent>false</MultiCurrencyDependent>
            <IsEditable>false</IsEditable>
            <HideCondition />
            <Width>-1</Width>
            <CustomFormatter />
            <AbbreviationLength>0</AbbreviationLength>
          </QFSDataPhoneCol>
          <QFSDataPickListCol>
            <StyleScheme />
            <DataField>ERPBillTo.ErpStatus</DataField>
            <ColumnId>66f2467f-3471-46f8-aeab-7a80748966a9</ColumnId>
            <HorizontalAlignment>left</HorizontalAlignment>
            <HeaderAlignment>left</HeaderAlignment>
            <SortDirection>None</SortDirection>
            <IsSortable>true</IsSortable>
            <SortField>ERPBillTo.ErpStatus</SortField>
            <MultiCurrencyDependent>false</MultiCurrencyDependent>
            <IsEditable>false</IsEditable>
            <HideCondition />
            <Width>-1</Width>
            <CustomFormatter />
            <AbbreviationLength>0</AbbreviationLength>
            <PickListName>ErpBillToStatus</PickListName>
            <DisplayMode>AsText</DisplayMode>
            <StorageMode>Code</StorageMode>
          </QFSDataPickListCol>
          <QFEditableCol>
            <StyleScheme />
            <DataField>ERPBillTo.ErpAccountingEntityId</DataField>
            <ColumnId>b0f947e6-63ad-482a-b459-fee938e4ae35</ColumnId>
            <HorizontalAlignment>left</HorizontalAlignment>
            <HeaderAlignment>left</HeaderAlignment>
            <SortDirection>None</SortDirection>
            <IsSortable>true</IsSortable>
            <SortField>ERPBillTo.ErpAccountingEntityId</SortField>
            <MultiCurrencyDependent>false</MultiCurrencyDependent>
            <IsEditable>false</IsEditable>
            <HideCondition />
            <Width>-1</Width>
            <CustomFormatter />
            <AbbreviationLength>0</AbbreviationLength>
          </QFEditableCol>
          <QFEditableCol>
            <StyleScheme />
            <DataField>ERPBillTo.ErpExtId</DataField>
            <ColumnId>93564eea-114e-42ad-94c6-cc1142d9df08</ColumnId>
            <HorizontalAlignment>left</HorizontalAlignment>
            <HeaderAlignment>left</HeaderAlignment>
            <SortDirection>None</SortDirection>
            <IsSortable>true</IsSortable>
            <SortField>ERPBillTo.ErpExtId</SortField>
            <MultiCurrencyDependent>false</MultiCurrencyDependent>
            <IsEditable>false</IsEditable>
            <HideCondition />
            <Width>-1</Width>
            <CustomFormatter />
            <AbbreviationLength>0</AbbreviationLength>
          </QFEditableCol>
        </Columns>
        <ConditionalWhere />
        <Select />
        <Include />
        <FeedCategory>InternalAppEntities</FeedCategory>
        <OnGetMappingId />
        <ParentRelationshipPropertyName>ERPPayFrom</ParentRelationshipPropertyName>
        <ChildRelationshipPropertyName>ERPBillTo</ChildRelationshipPropertyName>
        <OnDataChange />
        <OnAdd />
        <Tools />
      </QFSDataGrid>
    </Control>
  </Controls>
  <ToolControls>
    <Control typeName="Sage.Platform.QuickForms.Controls.QFElementSpacer, Sage.Platform.QuickForms">
      <QFElementSpacer>
        <Column>0</Column>
        <Row>0</Row>
        <HotKey>0</HotKey>
        <TabIndex>0</TabIndex>
        <ControlId>c344e8e08104e6eb6417c4c6b43abc6</ControlId>
        <DataBindings />
        <ControlLabelPlacement>left</ControlLabelPlacement>
        <ExtendedProperties />
        <CaptionAlignment>left</CaptionAlignment>
        <StyleScheme />
      </QFElementSpacer>
    </Control>
    <Control typeName="Sage.Platform.QuickForms.Controls.QFElementSpacer, Sage.Platform.QuickForms">
      <QFElementSpacer>
        <Column>0</Column>
        <Row>0</Row>
        <HotKey>0</HotKey>
        <TabIndex>0</TabIndex>
        <ControlId>ba39500a71e24dc4a531e1d14f26f084</ControlId>
        <DataBindings />
        <ControlLabelPlacement>left</ControlLabelPlacement>
        <ExtendedProperties />
        <CaptionAlignment>left</CaptionAlignment>
        <StyleScheme />
      </QFElementSpacer>
    </Control>
  </ToolControls>
  <Columns>
    <ColumnStyle>
      <SizeType>Percent</SizeType>
      <Width>100</Width>
    </ColumnStyle>
  </Columns>
  <Rows>
    <RowStyle>
      <SizeType>Absolute</SizeType>
      <Height>35</Height>
    </RowStyle>
  </Rows>
  <Description />
  <UseEntityNameAsTitle>true</UseEntityNameAsTitle>
  <EntityTypeName>IERPPayFrom</EntityTypeName>
  <DefaultNamespace>Sage.Entity.Interfaces</DefaultNamespace>
  <AssemblyName>Sage.Entity.Interfaces</AssemblyName>
</QuickForm>