<?xml version="1.0"?>
<method xmlns:xsi="http://www.w3.org/2001/XMLSchema-instance" xmlns:xsd="http://www.w3.org/2001/XMLSchema" id="062cbb90-53d7-4c21-8734-cb9446bd716a" lastModifiedUtc="2012-07-05T21:25:51.3085658Z" name="OnBeforeDelete" methodType="CrudEvent" actionType="None" returnMode="None">
  <extendedMetaData />
  <ExtendedPropertiesCollection>
    <extendee type="Sage.Platform.Orm.Entities.OrmEntityMethod" />
  </ExtendedPropertiesCollection>
  <parameter />
  <preExecuteTargets />
  <methodTargets>
    <methodTarget id="b8a883db-a73a-4122-866c-9b5cd916c78f" lastModifiedUtc="2012-07-05T21:25:51.1522848Z" targetType="Sage.Platform.Orm.DefaultCRUDEventHandler, Sage.Platform" targetMethod="OnBeforeDelete" active="true">
      <ExtendedPropertiesCollection>
        <extendee type="Sage.Platform.Orm.Entities.OrmMethodTarget" />
      </ExtendedPropertiesCollection>
    </methodTarget>
  </methodTargets>
  <postExecuteTargets />
  <postFlushTargets />
</method>