<?xml version="1.0"?>
<method xmlns:xsi="http://www.w3.org/2001/XMLSchema-instance" xmlns:xsd="http://www.w3.org/2001/XMLSchema" id="ae78370e-85ec-4d96-96b1-4f930fa644e8" lastModifiedUtc="2016-06-14T21:34:34.7253747Z" name="DocCalculateSalesPotential" methodType="Rule" actionType="None" returnMode="None">
  <extendedMetaData />
  <ExtendedPropertiesCollection>
    <extendee type="Sage.Platform.Orm.Entities.OrmEntityMethod" />
  </ExtendedPropertiesCollection>
  <parameter />
  <preExecuteTargets />
  <methodTargets>
    <methodTarget id="8d2d10e2-f21a-4a30-96e6-1d4e3bb82c21" lastModifiedUtc="2016-06-14T21:34:32.9031925Z" targetType="Sage.SalesLogix.Opportunity.Rules, Sage.SalesLogix.BusinessRules" targetMethod="DocCalculateSalesPotential" active="true">
      <ExtendedPropertiesCollection>
        <extendee type="Sage.Platform.Orm.Entities.OrmMethodTarget" />
      </ExtendedPropertiesCollection>
    </methodTarget>
  </methodTargets>
  <postExecuteTargets />
</method>