<?xml version="1.0"?>
<method xmlns:xsi="http://www.w3.org/2001/XMLSchema-instance" xmlns:xsd="http://www.w3.org/2001/XMLSchema" id="138c3778-d9ec-4601-b15e-4aa79e5e963c" lastModifiedUtc="2017-09-15T09:35:27.0658673Z" name="RePriceOpportunity" returnType="String" methodType="Rule" actionType="None" returnMode="Object" isInstance="false">
  <extendedMetaData />
  <ExtendedPropertiesCollection>
    <extendee type="Sage.Platform.Orm.Entities.OrmEntityMethod" />
  </ExtendedPropertiesCollection>
  <parameter>
    <OrmEntityMethodParam id="0f9985fc-6852-4e14-9cba-5342f4dc0cc5" paramName="options" sequence="0" paramType="String">
      <description>Options required to call the pricing and availability service.</description>
    </OrmEntityMethodParam>
  </parameter>
  <preExecuteTargets />
  <methodTargets>
    <methodTarget id="b30555bb-2bc0-41ab-99a5-252983ec29fb" lastModifiedUtc="2017-09-15T09:36:09.1640158Z" targetType="Sage.SalesLogix.Opportunity.Rules, Sage.SalesLogix.BusinessRules" targetMethod="RePriceOpportunity" active="true">
      <ExtendedPropertiesCollection>
        <extendee type="Sage.Platform.Orm.Entities.OrmMethodTarget" />
      </ExtendedPropertiesCollection>
    </methodTarget>
  </methodTargets>
  <postExecuteTargets />
</method>