<?xml version="1.0"?>
<entity xmlns:xsi="http://www.w3.org/2001/XMLSchema-instance" xmlns:xsd="http://www.w3.org/2001/XMLSchema" id="716da65d-4a3f-4efe-86f3-f908222a6cc4" lastModifiedUtc="2017-09-12T14:39:55.3357687Z" manageSchema="false" tableName="ERPINVOICEAGINGVIEW" name="ERPInvoiceAgingView" displayPropertyId="893e1ce5-07ff-447a-b75f-22af7585a58c" isExtension="false" audited="false">
  <extendedMetaData />
  <ExtendedPropertiesCollection>
    <extendee type="Sage.Platform.Orm.Entities.OrmEntity">
      <extender guid="1589723d-0536-4bf3-bdd7-3f6f7fe165d0">
        <OrmEntityMetadataExtension>
          <StringExpression>${AgingInvoices}</StringExpression>
          <IsHistoryTable>false</IsHistoryTable>
        </OrmEntityMetadataExtension>
      </extender>
      <extender guid="76aa0e24-2c8f-3b71-a1f9-ca6db3db4459">
        <OrmEntitySDataExtension generateFeed="true" pathName="erpInvoiceAgingView" canPost="true" canPut="true" canDelete="true" />
      </extender>
      <extender guid="7ba306ee-9fbc-4c61-98be-bcfd895410ee">
        <OrmEntityImportExtension />
      </extender>
      <extender guid="0878d6db-0383-4cd2-ae88-0e1f6cf9ecd5">
        <OrmEntityBulkActionExtension />
      </extender>
    </extendee>
  </ExtendedPropertiesCollection>
  <keyProperties>
    <keyReference id="b3496b0d-9a92-450c-9e95-35fa52f89822" ordinalPosition="1" />
  </keyProperties>
  <properties>
    <property xsi:type="OrmFieldProperty" id="893e1ce5-07ff-447a-b75f-22af7585a58c" lastModifiedUtc="2017-06-14T15:05:30.0695351Z" name="AgingInvoices" audited="false" columnName="AGINGINVOICES" maxLength="0" precision="10" scale="0" ordinal="0" isReadOnly="false">
      <ExtendedPropertiesCollection>
        <extendee type="Sage.Platform.Orm.Entities.OrmFieldProperty">
          <extender guid="ae60621d-9d91-3d9a-b9fb-eb6c8be12131">
            <OrmEntityPropertySDataExtension generate="true" />
          </extender>
          <extender guid="ac7a8695-7689-4c4b-819d-6c3ab7c2e15f">
            <OrmEntityPropertyImportExtension />
          </extender>
          <extender guid="cbb948ad-9154-4174-847a-690a81c1c2e4">
            <OrmEntityPropertyBulkActionExtension />
          </extender>
        </extendee>
      </ExtendedPropertiesCollection>
      <SystemDataType guid="47f90249-e4c8-4564-9ae6-e1fa9904f8b8">
        <IntegerDataType />
      </SystemDataType>
    </property>
    <property xsi:type="OrmFieldProperty" id="b3496b0d-9a92-450c-9e95-35fa52f89822" lastModifiedUtc="2017-06-14T05:29:15.0217014Z" name="PrimaryKeyId" audited="false" columnName="PRIMARYKEYID" maxLength="12" precision="0" scale="0" ordinal="1" isReadOnly="false">
      <ExtendedPropertiesCollection>
        <extendee type="Sage.Platform.Orm.Entities.OrmFieldProperty">
          <extender guid="ae60621d-9d91-3d9a-b9fb-eb6c8be12131">
            <OrmEntityPropertySDataExtension generate="true" />
          </extender>
          <extender guid="ac7a8695-7689-4c4b-819d-6c3ab7c2e15f">
            <OrmEntityPropertyImportExtension />
          </extender>
          <extender guid="cbb948ad-9154-4174-847a-690a81c1c2e4">
            <OrmEntityPropertyBulkActionExtension />
          </extender>
        </extendee>
      </ExtendedPropertiesCollection>
      <SystemDataType guid="30053f5a-8d40-4db1-b185-1e4128eb26cc">
        <StandardIdDataType />
      </SystemDataType>
    </property>
    <property xsi:type="OrmFieldProperty" id="d9d30808-b5dc-4896-94ef-8a95da2af6b0" lastModifiedUtc="2017-06-14T15:05:30.0705351Z" name="DaysLateClass" audited="false" columnName="DAYSLATECLASS" maxLength="6" precision="0" scale="0" ordinal="2" isReadOnly="false">
      <ExtendedPropertiesCollection>
        <extendee type="Sage.Platform.Orm.Entities.OrmFieldProperty">
          <extender guid="ae60621d-9d91-3d9a-b9fb-eb6c8be12131">
            <OrmEntityPropertySDataExtension generate="true" />
          </extender>
          <extender guid="ac7a8695-7689-4c4b-819d-6c3ab7c2e15f">
            <OrmEntityPropertyImportExtension />
          </extender>
          <extender guid="cbb948ad-9154-4174-847a-690a81c1c2e4">
            <OrmEntityPropertyBulkActionExtension />
          </extender>
        </extendee>
      </ExtendedPropertiesCollection>
      <SystemDataType guid="ccc0f01d-7ba5-408e-8526-a3f942354b3a">
        <TextDataType>
          <Length>6</Length>
        </TextDataType>
      </SystemDataType>
    </property>
    <property xsi:type="OrmFieldProperty" id="12feb9f4-1bcc-44e0-b176-4fd645f2d33c" lastModifiedUtc="2017-06-14T15:05:30.0705351Z" name="Total" audited="false" columnName="TOTAL" maxLength="0" precision="53" scale="0" ordinal="3" isReadOnly="false">
      <ExtendedPropertiesCollection>
        <extendee type="Sage.Platform.Orm.Entities.OrmFieldProperty">
          <extender guid="ae60621d-9d91-3d9a-b9fb-eb6c8be12131">
            <OrmEntityPropertySDataExtension generate="true" />
          </extender>
          <extender guid="ac7a8695-7689-4c4b-819d-6c3ab7c2e15f">
            <OrmEntityPropertyImportExtension />
          </extender>
          <extender guid="cbb948ad-9154-4174-847a-690a81c1c2e4">
            <OrmEntityPropertyBulkActionExtension />
          </extender>
        </extendee>
      </ExtendedPropertiesCollection>
      <SystemDataType guid="f37c635c-9fbf-40d8-98d5-750a54a3cca1">
        <DoubleDataType />
      </SystemDataType>
    </property>
    <property xsi:type="OrmFieldProperty" id="4f4a1188-f531-4cef-8e90-8befca1eeff8" lastModifiedUtc="2017-06-14T15:05:30.0705351Z" name="AccountId" audited="false" include="false" columnName="ACCOUNTID" maxLength="12" precision="0" scale="0" ordinal="4" isReadOnly="false">
      <ExtendedPropertiesCollection>
        <extendee type="Sage.Platform.Orm.Entities.OrmFieldProperty">
          <extender guid="ae60621d-9d91-3d9a-b9fb-eb6c8be12131">
            <OrmEntityPropertySDataExtension generate="true" />
          </extender>
          <extender guid="ac7a8695-7689-4c4b-819d-6c3ab7c2e15f">
            <OrmEntityPropertyImportExtension />
          </extender>
          <extender guid="cbb948ad-9154-4174-847a-690a81c1c2e4">
            <OrmEntityPropertyBulkActionExtension />
          </extender>
        </extendee>
      </ExtendedPropertiesCollection>
      <SystemDataType guid="30053f5a-8d40-4db1-b185-1e4128eb26cc">
        <StandardIdDataType />
      </SystemDataType>
    </property>
    <property xsi:type="OrmFieldProperty" id="580666b4-47e0-45df-9215-d200988a2f7d" lastModifiedUtc="2017-09-12T14:25:33.6893269Z" name="MaxDaysLate" audited="false" columnName="MAXDAYSLATE" maxLength="0" precision="10" scale="0" ordinal="7" isReadOnly="false">
      <ExtendedPropertiesCollection>
        <extendee type="Sage.Platform.Orm.Entities.OrmFieldProperty">
          <extender guid="ae60621d-9d91-3d9a-b9fb-eb6c8be12131">
            <OrmEntityPropertySDataExtension generate="true" />
          </extender>
          <extender guid="ac7a8695-7689-4c4b-819d-6c3ab7c2e15f">
            <OrmEntityPropertyImportExtension />
          </extender>
          <extender guid="cbb948ad-9154-4174-847a-690a81c1c2e4">
            <OrmEntityPropertyBulkActionExtension />
          </extender>
        </extendee>
      </ExtendedPropertiesCollection>
      <SystemDataType guid="47f90249-e4c8-4564-9ae6-e1fa9904f8b8">
        <IntegerDataType />
      </SystemDataType>
    </property>
  </properties>
</entity>